casuallite/__init__.py
casuallite/rcse_ibfs.py
casuallite-0.1.1.dist-info/METADATA
casuallite-0.1.1.dist-info/WHEEL
casuallite-0.1.1.dist-info/top_level.txt
casuallite-0.1.1.dist-info/RECORD
