Metadata-Version: 2.1
Name: casuallite
Version: 0.1.1
Summary: CasualLite: The world's first Hybrid Meta Causal Learning Algorithm
Home-page: https://github.com/theAiAlgoRepository/casuallite
Author: Project Genesis
Author-email: srinimagi99@gmail.com
License: Apache-2.0
Classifier: Programming Language :: Python :: 3
Classifier: License :: OSI Approved :: Apache Software License
Classifier: Operating System :: OS Independent
Classifier: Topic :: Scientific/Engineering :: Artificial Intelligence
Requires-Python: >=3.8
Requires-Dist: numpy
Requires-Dist: seaborn
Requires-Dist: pandas
Requires-Dist: matplotlib
Requires-Dist: scikit-learn
Requires-Dist: scipy
Requires-Dist: torch
Requires-Dist: networkx
